chatbees/.DS_Store
chatbees/__init__.py
chatbees/client/__init__.py
chatbees/client/admin_management.py
chatbees/client/collection_management.py
chatbees/client_models/__init__.py
chatbees/client_models/chat.py
chatbees/client_models/collection.py
chatbees/server_models/__init__.py
chatbees/server_models/admin_api.py
chatbees/server_models/chat.py
chatbees/server_models/collection_api.py
chatbees/server_models/doc_api.py
chatbees/server_models/feedback_api.py
chatbees/server_models/ingestion_api.py
chatbees/server_models/ingestion_type.py
chatbees/server_models/search_api.py
chatbees/tests/api_surface_test.py
chatbees/tests/data/española.txt
chatbees/tests/data/française.txt
chatbees/tests/data/test_audio.mp3
chatbees/tests/data/text_file.txt
chatbees/tests/data/中文.txt
chatbees/tests/regression_test.py
chatbees/utils/__init__.py
chatbees/utils/ask.py
chatbees/utils/config.py
chatbees/utils/exceptions.py
chatbees/utils/file_upload.py
chatbees_python_client-1.2.8.dist-info/LICENSE
chatbees_python_client-1.2.8.dist-info/METADATA
chatbees_python_client-1.2.8.dist-info/WHEEL
chatbees_python_client-1.2.8.dist-info/RECORD
