Metadata-Version: 2.1
Name: chatbees-python-client
Version: 1.2.8
Summary: Python client for ChatBees
Author: ChatBees
Author-email: build@chatbees.ai
Requires-Python: >=3.10,<4.0
Classifier: Programming Language :: Python :: 3
Classifier: Programming Language :: Python :: 3.10
Classifier: Programming Language :: Python :: 3.11
Classifier: Programming Language :: Python :: 3.12
Classifier: Programming Language :: Python :: 3.13
Requires-Dist: croniter (>=2.0.5,<3.0.0)
Requires-Dist: pydantic (>=2.4.2,<3.0.0)
Requires-Dist: requests (>=2.31.0,<3.0.0)
Requires-Dist: shortuuid (>=1.0.13,<2.0.0)
